django_shared_property/__init__.py
django_shared_property/apps.py
django_shared_property/decorator.py
django_shared_property/expressions.py
django_shared_property/parser.py
django_shared_property-0.8.0.dist-info/LICENSE
django_shared_property-0.8.0.dist-info/WHEEL
django_shared_property-0.8.0.dist-info/METADATA
django_shared_property-0.8.0.dist-info/RECORD
