Metadata-Version: 2.1
Name: django-shared-property
Version: 0.8.0
Summary: Properties that are both ORM expressions and python code.
Home-page: https://django-shared-property.readthedocs.io
License: MIT
Author: Matthew Schinckel
Author-email: matt@schinckel.net
Requires-Python: >3.8
Classifier: Development Status :: 2 - Pre-Alpha
Classifier: Intended Audience :: Developers
Classifier: License :: OSI Approved :: MIT License
Classifier: Natural Language :: English
Classifier: Programming Language :: Python :: 3
Classifier: Programming Language :: Python :: 3.9
Classifier: Programming Language :: Python :: 3.10
Classifier: Programming Language :: Python :: 3.11
Classifier: Programming Language :: Python :: 3.10
Classifier: Programming Language :: Python :: 3.6
Classifier: Programming Language :: Python :: 3.7
Classifier: Programming Language :: Python :: 3.8
Classifier: Programming Language :: Python :: 3.9
Project-URL: Repository, https://github.com/schinckel/django-shared-property
